README.md
setup.cfg
setup.py
Relatorio_Ensalamento/Relatorio_Ensalamento.py
Relatorio_Ensalamento/__init__.py
Relatorio_Ensalamento.egg-info/PKG-INFO
Relatorio_Ensalamento.egg-info/SOURCES.txt
Relatorio_Ensalamento.egg-info/dependency_links.txt
Relatorio_Ensalamento.egg-info/top_level.txt
Sugestao/Sugestao.py
Sugestao/__init__.py
Unificar_XML/Unificar_XML.py
Unificar_XML/__init__.py