Metadata-Version: 2.1
Name: Relatorio-Ensalamento
Version: 2.4.7
Summary: Conversor utilizado para a geração do relatorio ensalamento
Home-page: UNKNOWN
Author: Matheus Henrique Rosa
Author-email: m.rosa1@pucpr.br
License: MIT
Keywords: conversor relatorio ensalamento
Platform: UNKNOWN
